connegp/__init__.py
connegp-0.2.dist-info/LICENSE
connegp-0.2.dist-info/METADATA
connegp-0.2.dist-info/WHEEL
connegp-0.2.dist-info/top_level.txt
connegp-0.2.dist-info/RECORD
