Metadata-Version: 1.1
Name: connegp
Version: 0.2
Summary: This small library module assists with tasks related to Content Negotiation by Profile
Home-page: https://github.com/nicholascar/connegp
Author: Nicholas Car
Author-email: nicholas.car@surroundaustralia.com
License: LICENSE
Download-URL: https://github.com/nicholascar/connegp/archive/v0.2.tar.gz
Project-URL: Bug Reports, https://github.com/nicholascar/connegp/issues
Project-URL: Source, https://github.com/nicholascar/connegp
Keywords: Content Negotiation,HTTP,Linked Data,Semantic Web,Python,API,RDF
Platform: UNKNOWN
Classifier: Development Status :: 4 - Beta
Classifier: Topic :: Utilities
Classifier: License :: OSI Approved :: GNU General Public License v3 or later (GPLv3+)
Classifier: Intended Audience :: Developers
Classifier: Natural Language :: English
Classifier: Programming Language :: Python :: 3
Classifier: Programming Language :: Python :: 3 :: Only
Classifier: Programming Language :: Python :: 3.4
Classifier: Programming Language :: Python :: 3.5
Classifier: Programming Language :: Python :: 3.6
Classifier: Programming Language :: Python :: 3.7
Classifier: Programming Language :: Python :: Implementation :: CPython
Classifier: Programming Language :: Python :: Implementation :: PyPy
Classifier: Topic :: Software Development :: Libraries :: Python Modules
